LICENSE
README.md
lyystkcode.py
setup.py
lyystkcode.egg-info/PKG-INFO
lyystkcode.egg-info/SOURCES.txt
lyystkcode.egg-info/dependency_links.txt
lyystkcode.egg-info/requires.txt
lyystkcode.egg-info/top_level.txt