Metadata-Version: 2.1
Name: lyystkcode
Version: 1.11
Summary: userfull application for  lyy
Author: lyy
Author-email: 
License: MIT
License-File: LICENSE
Requires-Dist: pandas
Requires-Dist: baostock
Requires-Dist: tushare
Requires-Dist: sqlalchemy
